mgqpy/__init__.py
mgqpy/utils.py
mgqpy/operators/all.py
mgqpy/operators/and_or_nor.py
mgqpy/operators/elem_match.py
mgqpy/operators/eq_ne_not.py
mgqpy/operators/gt.py
mgqpy/operators/gte.py
mgqpy/operators/in_nin.py
mgqpy/operators/lt.py
mgqpy/operators/lte.py
mgqpy/operators/mod.py
mgqpy/operators/regex.py
mgqpy/operators/size.py
mgqpy-0.7.2.dist-info/licenses/LICENSE
mgqpy-0.7.2.dist-info/WHEEL
mgqpy-0.7.2.dist-info/METADATA
mgqpy-0.7.2.dist-info/RECORD
