Metadata-Version: 2.4
Name: mgqpy
Version: 0.7.2
Summary: mongo query as a predicate function
Author-email: Chiawei Ong <ongchiawei@gmail.com>
Classifier: License :: OSI Approved :: MIT License
License-File: LICENSE
Project-URL: Home, https://github.com/weiliddat/mgqpy
